slurmutils/__init__.py
slurmutils/acctgather.py
slurmutils/acctgather.pyi
slurmutils/cgroup.py
slurmutils/cgroup.pyi
slurmutils/exceptions.py
slurmutils/gres.py
slurmutils/gres.pyi
slurmutils/oci.py
slurmutils/oci.pyi
slurmutils/py.typed
slurmutils/slurm.py
slurmutils/slurm.pyi
slurmutils/slurmdbd.py
slurmutils/slurmdbd.pyi
slurmutils/utils.py
slurmutils/core/__init__.py
slurmutils/core/base.py
slurmutils/core/callback.py
slurmutils/core/editor.py
slurmutils/core/schema.py
slurmutils-1.2.0.dist-info/METADATA
slurmutils-1.2.0.dist-info/WHEEL
slurmutils-1.2.0.dist-info/licenses/LICENSE
slurmutils-1.2.0.dist-info/RECORD
