Metadata-Version: 2.4
Name: slurmutils
Version: 1.2.0
Summary: Utilities and APIs for interfacing with the Slurm workload manager.
Project-URL: repository, https://github.com/charmed-hpc/slurmutils
Project-URL: issues, https://github.com/charmed-hpc/slurmutils/issues
Author-email: "Jason C. Nucciarone" <nuccitheboss@ubuntu.com>
Maintainer-email: "Jason C. Nucciarone" <nuccitheboss@ubuntu.com>, Ubuntu High-Performance Computing <hpc-ubuntu-group@canonical.com>
License-Expression: LGPL-3.0-only
License-File: LICENSE
Keywords: HPC,administration,orchestration,utility
Classifier: Development Status :: 4 - Beta
Classifier: Intended Audience :: Developers
Classifier: Intended Audience :: Science/Research
Classifier: License :: OSI Approved :: GNU Lesser General Public License v3 (LGPLv3)
Classifier: Operating System :: POSIX :: Linux
Classifier: Programming Language :: Python :: 3.10
Classifier: Programming Language :: Python :: 3.11
Classifier: Programming Language :: Python :: 3.12
Classifier: Programming Language :: Python :: 3.13
Requires-Python: >=3.10
Requires-Dist: jsonschema~=4.23
Requires-Dist: typing-extensions~=4.14
Provides-Extra: dev
Requires-Dist: codespell; extra == 'dev'
Requires-Dist: coverage[toml]~=7.6; extra == 'dev'
Requires-Dist: pyfakefs~=5.9; extra == 'dev'
Requires-Dist: pyright; extra == 'dev'
Requires-Dist: pytest~=8.3; extra == 'dev'
Requires-Dist: ruff; extra == 'dev'
